viper/__init__.py
viper/functions.py
viper/data/__init__.py
viper/data/mtcars.csv
viper_df-0.0.7.dist-info/METADATA
viper_df-0.0.7.dist-info/WHEEL
viper_df-0.0.7.dist-info/licenses/LICENSE
viper_df-0.0.7.dist-info/RECORD
