Metadata-Version: 2.1
Name: viper-df
Version: 0.0.7
Summary: Simple, expressive pipeline syntax to transform and manipulate data with ease
Project-URL: Homepage, https://github.com/aropele/viper
Project-URL: Bug Tracker, https://github.com/aropele/viper/issues
Author-email: Andrea Ropele <andrea.ropele@gmail.com>
License-File: LICENSE
Classifier: License :: OSI Approved :: MIT License
Classifier: Operating System :: OS Independent
Classifier: Programming Language :: Python :: 3
Requires-Python: >=3.8
Requires-Dist: pandas
